{
  "parent": "minecraft:recipes/root",
  "criteria": {
    "has_electric_press": {
      "conditions": {
        "items": [
          {
            "items": [
              "idkmod:electric_press"
            ]
          }
        ]
      },
      "trigger": "minecraft:inventory_changed"
    },
    "has_the_recipe": {
      "conditions": {
        "recipe": "idkmod:alloy_furnace"
      },
      "trigger": "minecraft:recipe_unlocked"
    }
  },
  "requirements": [
    [
      "has_electric_press",
      "has_the_recipe"
    ]
  ],
  "rewards": {
    "recipes": [
      "idkmod:alloy_furnace"
    ]
  },
  "sends_telemetry_event": false
}